kgiapp-2021.1.1.data/purelib/kgiapp/__init__.py
kgiapp-2021.1.1.data/purelib/kgiapp/.ipynb_checkpoints/__init__-checkpoint.py
kgiapp-2021.1.1.data/purelib/kgiapp/Quote/ICSharpCode.SharpZipLib.dll
kgiapp-2021.1.1.data/purelib/kgiapp/Quote/Package.dll
kgiapp-2021.1.1.data/purelib/kgiapp/Quote/PushClient.dll
kgiapp-2021.1.1.data/purelib/kgiapp/Quote/QuoteCom.dll
kgiapp-2021.1.1.data/purelib/kgiapp/Quote/__init__.py
kgiapp-2021.1.1.data/purelib/kgiapp/Quote/common.py
kgiapp-2021.1.1.data/purelib/kgiapp/Quote/event.py
kgiapp-2021.1.1.data/purelib/kgiapp/Quote/quote.py
kgiapp-2021.1.1.data/purelib/kgiapp/Trade/ICSharpCode.SharpZipLib.dll
kgiapp-2021.1.1.data/purelib/kgiapp/Trade/Interop.KGICGCAPIATLLib.dll
kgiapp-2021.1.1.data/purelib/kgiapp/Trade/Package.dll
kgiapp-2021.1.1.data/purelib/kgiapp/Trade/PushClient.dll
kgiapp-2021.1.1.data/purelib/kgiapp/Trade/System
kgiapp-2021.1.1.data/purelib/kgiapp/Trade/TradeCom.dll
kgiapp-2021.1.1.data/purelib/kgiapp/Trade/__init__.py
kgiapp-2021.1.1.data/purelib/kgiapp/Trade/common.py
kgiapp-2021.1.1.data/purelib/kgiapp/Trade/constant.py
kgiapp-2021.1.1.data/purelib/kgiapp/Trade/errMsg.ini
kgiapp-2021.1.1.data/purelib/kgiapp/Trade/trade.py
kgiapp-2021.1.1.dist-info/LICENSE
kgiapp-2021.1.1.dist-info/METADATA
kgiapp-2021.1.1.dist-info/WHEEL
kgiapp-2021.1.1.dist-info/top_level.txt
kgiapp-2021.1.1.dist-info/RECORD
