Metadata-Version: 2.1
Name: kgiapp
Version: 2021.1.1
Summary: Python client for send order to Concords Securities.
Home-page: https://github.com/phymach
Author: Leo Wu
Author-email: phymach@gmail.com
License: MIT
Keywords: stock,futures,option,TWSE,TPEX,TAIFEX
Platform: Windows
Classifier: Development Status :: 4 - Beta
Classifier: License :: OSI Approved :: MIT License
Classifier: Intended Audience :: Developers
Classifier: Programming Language :: Python :: 3
Classifier: Programming Language :: Python :: 3.7
Classifier: Programming Language :: Python :: 3.8
Classifier: Programming Language :: Python :: 3.9
Classifier: Operating System :: Microsoft :: Windows
Classifier: Topic :: Office/Business :: Financial
Classifier: Topic :: Software Development :: Libraries
Classifier: Topic :: Software Development :: Libraries :: Python Modules
Requires-Python: >=3.7
Requires-Dist: pythonnet (>=2.5.1)
Requires-Dist: pandas
Requires-Dist: psutil
Requires-Dist: pywin32
